hello_ext/hello_cpp.h
hello_ext/hello_c.c
hello_ext/__init__.py
hello_ext/hello_c.h
hello_ext/_core.cpython-39-darwin.so
hello_ext/hello_cpp.cpp
hello_ext/bindings.cpp
hello_ext_demo-1.0.1.dist-info/RECORD
hello_ext_demo-1.0.1.dist-info/WHEEL
hello_ext_demo-1.0.1.dist-info/top_level.txt
hello_ext_demo-1.0.1.dist-info/METADATA
