Metadata-Version: 2.4
Name: hello-ext-demo
Version: 1.0.1
Summary: Minimal pybind11 extension demo package
Requires-Python: >=3.8
